LICENSE
MANIFEST.in
README.md
dive.py
setup.py
dive.egg-info/PKG-INFO
dive.egg-info/SOURCES.txt
dive.egg-info/dependency_links.txt
dive.egg-info/requires.txt
dive.egg-info/top_level.txt